swiv/__init__.py
swiv-4.0.0.dist-info/METADATA
swiv-4.0.0.dist-info/WHEEL
swiv-4.0.0.dist-info/top_level.txt
swiv-4.0.0.dist-info/RECORD
