Metadata-Version: 2.4
Name: swiv
Version: 4.0.0
Summary: PoC for Dependency Confusion with safe exfiltration simulation
Home-page: http://cwcypxwrelhwvpogwgwoyc1a57it46b77.oast.fun
Author: yourname
Author-email: your@email.com
Dynamic: author
Dynamic: author-email
Dynamic: home-page
Dynamic: summary
